ina228.py
micropython_ina228-0.1.0.dist-info/licenses/LICENSE
micropython_ina228-0.1.0.dist-info/METADATA
micropython_ina228-0.1.0.dist-info/WHEEL
micropython_ina228-0.1.0.dist-info/top_level.txt
micropython_ina228-0.1.0.dist-info/RECORD
