Metadata-Version: 2.4
Name: micropython-ina228
Version: 0.1.0
Summary: TI INA228 library for MicroPython
Author-email: Avram Lubkin <avylove@rockhopper.net>
License-Expression: MPL-2.0
Project-URL: Homepage, https://github.com/Rockhopper-Technologies/micropython-ina228
Keywords: micropython,TI,Texas Instruments,INA228,current,voltage,power
Classifier: Programming Language :: Python :: Implementation :: MicroPython
Classifier: Development Status :: 4 - Beta
Classifier: Intended Audience :: Developers
Classifier: Topic :: Software Development :: Embedded Systems
License-File: LICENSE
Dynamic: license-file
